WiFiQRGen/__init__.py
wifiqrgen-0.1.0.dist-info/METADATA
wifiqrgen-0.1.0.dist-info/WHEEL
wifiqrgen-0.1.0.dist-info/licenses/LICENSE
wifiqrgen-0.1.0.dist-info/RECORD
