Metadata-Version: 2.3
Name: WiFiQRGen
Version: 0.1.0
Summary: Python package that generates Wi-Fi QR Codes that can be scanned for easily connecting to Wi-Fi.
Project-URL: homepage, https://github.com/MelonSmasher/WiFiQRGen
Project-URL: issues, https://github.com/MelonSmasher/WiFiQRGen/issues
Project-URL: license, https://raw.githubusercontent.com/MelonSmasher/WiFiQRGen/master/LICENSE
Author: Alex Markessinis
License-File: LICENSE
Classifier: License :: OSI Approved :: MIT License
Classifier: Operating System :: OS Independent
Classifier: Programming Language :: Python :: 3
Requires-Python: >=3.8
